herschelhelp_internal/__init__.py
herschelhelp_internal/flagging.py
herschelhelp_internal/masterlist.py
herschelhelp_internal/starmask.py
herschelhelp_internal/utils.py
herschelhelp_internal-1.0.5.dist-info/LICENSE
herschelhelp_internal-1.0.5.dist-info/METADATA
herschelhelp_internal-1.0.5.dist-info/WHEEL
herschelhelp_internal-1.0.5.dist-info/top_level.txt
herschelhelp_internal-1.0.5.dist-info/RECORD
