Metadata-Version: 2.2
Name: herschelhelp_internal
Version: 1.0.5
Summary: HELP project internal code
Author: Yannick Roehlly
Author-email: yannick.roehlly@lam.fr
License: MIT
License-File: LICENSE
Requires-Dist: numpy
Requires-Dist: astropy
Requires-Dist: pymoc
Requires-Dist: healpy
Requires-Dist: sfdmap2
Requires-Dist: seaborn
Requires-Dist: matplotlib-venn
Requires-Dist: pyyaml
Requires-Dist: pyregion==1.2.0
Requires-Dist: humanfriendly
Dynamic: author
Dynamic: author-email
Dynamic: description
Dynamic: license
Dynamic: requires-dist
Dynamic: summary
